ptblop/__init__.py
ptblop/_version.py
ptblop/core.py
ptblop/prunable_block.py
ptblop/py.typed
ptblop/utils.py
ptblop/wrapper_timm/__init__.py
ptblop/wrapper_timm/vision_transformer.py
ptblop/wrapper_transformers/__init__.py
ptblop/wrapper_transformers/common.py
ptblop/wrapper_transformers/llama3.py
ptblop/wrapper_transformers/phi2.py
ptblop/wrapper_transformers/qwen2.py
ptblop/wrapper_transformers/qwen3.py
ptblop/wrapper_transformers/qwen3_moe.py
ptblop/wrapper_transformers_pre448/__init__.py
ptblop/wrapper_transformers_pre448/common.py
ptblop/wrapper_transformers_pre448/llama3.py
ptblop/wrapper_transformers_pre448/phi2.py
ptblop/wrapper_transformers_pre448/qwen2.py
ptblop-0.4.0.dist-info/licenses/LICENSE
ptblop-0.4.0.dist-info/METADATA
ptblop-0.4.0.dist-info/WHEEL
ptblop-0.4.0.dist-info/top_level.txt
ptblop-0.4.0.dist-info/RECORD
