Metadata-Version: 2.4
Name: ptblop
Version: 0.4.0
Summary: Package containing builders for block-pruned transformer models in PyTorch
Author: lopusz
License-Expression: Apache-2.0
Project-URL: homepage, https://github.com/michal-lopuszynski-tcl/ptblop/tree/main/ptblop
Classifier: Programming Language :: Python :: 3
Requires-Python: >=3.10
License-File: LICENSE
Requires-Dist: torch
Dynamic: license-file
